tosfs/__init__.py
tosfs/certification.py
tosfs/compatible.py
tosfs/consts.py
tosfs/core.py
tosfs/exceptions.py
tosfs/fsspec_utils.py
tosfs/models.py
tosfs/retry.py
tosfs/tag.py
tosfs/tests/.gitkeep
tosfs/tests/conftest.py
tosfs/tests/test_certification.py
tosfs/tests/test_fsspec_api.py
tosfs/tests/test_fsspec_integration.py
tosfs/tests/test_logging.py
tosfs/tests/test_retry.py
tosfs/tests/test_stability.py
tosfs/tests/test_tag.py
tosfs/tests/test_tosfs.py
tosfs/tests/test_utils.py
tosfs/utils.py
tosfs/version.py
tosfs-2025.6.0.dist-info/LICENSE
tosfs-2025.6.0.dist-info/METADATA
tosfs-2025.6.0.dist-info/WHEEL
tosfs-2025.6.0.dist-info/RECORD
