Metadata-Version: 2.3
Name: tosfs
Version: 2025.6.0
Summary: TOSFS is a Pythonic file-system interface for TOS（Tinder Object Storage）.
License: Apache-2.0
Keywords: fsspec,tos,volcengine
Author: Vino Yang
Author-email: yanghua@bytedance.com
Requires-Python: >=3.9,<4.0
Classifier: Development Status :: 4 - Beta
Classifier: Intended Audience :: Developers
Classifier: License :: OSI Approved :: Apache Software License
Classifier: Operating System :: OS Independent
Classifier: Programming Language :: Python :: 3
Classifier: Programming Language :: Python :: 3.9
Classifier: Programming Language :: Python :: 3.10
Classifier: Programming Language :: Python :: 3.11
Classifier: Programming Language :: Python :: 3.12
Classifier: Programming Language :: Python :: 3.13
Requires-Dist: fsspec (>=2023.5.0)
Requires-Dist: tos (>=2.8.0)
Requires-Dist: volcengine (>=1.0.154,<2.0.0)
Project-URL: Documentation, https://tosfs.readthedocs.io/en/latest/
Project-URL: Homepage, https://github.com/fsspec/tosfs
Project-URL: Repository, https://github.com/fsspec/tosfs
